MANIFEST.in
README.rst
setup.py
configurableproduct/__init__.py
configurableproduct/admin.py
configurableproduct/tests.py
configurableproduct/locale/ru/LC_MESSAGES/django.mo
configurableproduct/locale/ru/LC_MESSAGES/django.po
configurableproduct/migrations/0001_initial.py
configurableproduct/migrations/0002_add_type_through.py
configurableproduct/migrations/0003_migrate_fields.py
configurableproduct/migrations/0004_apply_though.py
configurableproduct/migrations/__init__.py
configurableproduct/models/__init__.py
configurableproduct/models/product.py
configurableproduct/models/producttypes.py
configurableproduct/models/fields/__init__.py
configurableproduct/models/fields/abstract.py
configurableproduct/models/fields/boolean_field.py
configurableproduct/models/fields/char_field.py
configurableproduct/models/fields/float_field.py
configurableproduct/models/fields/image_field.py
django_shop_configurableproduct.egg-info/PKG-INFO
django_shop_configurableproduct.egg-info/SOURCES.txt
django_shop_configurableproduct.egg-info/dependency_links.txt
django_shop_configurableproduct.egg-info/requires.txt
django_shop_configurableproduct.egg-info/top_level.txt