Metadata-Version: 1.0
Name: django-shop-configurableproduct
Version: 0.3.1
Summary: Configurable product for django-shop
Home-page: https://bitbucket.org/zeus/django-shop-configurableproduct
Author: Pavel Zhukov
Author-email: gelios@gmail.com
License: GPL
Keywords: django-shop,product
Platform: UNKNOWN
